desmy_python/__init__.py
desmy_python/models.py
tests/__init__.py
tests/models.py
tests/test_models.py
desmy_python-0.1.0.dist-info/LICENSE
desmy_python-0.1.0.dist-info/METADATA
desmy_python-0.1.0.dist-info/WHEEL
desmy_python-0.1.0.dist-info/top_level.txt
desmy_python-0.1.0.dist-info/RECORD
